admindojo/__init__.py
admindojo/admindojo.py
admindojo/cli.py
admindojo-0.1.28.dist-info/AUTHORS.rst
admindojo-0.1.28.dist-info/LICENSE
admindojo-0.1.28.dist-info/METADATA
admindojo-0.1.28.dist-info/WHEEL
admindojo-0.1.28.dist-info/entry_points.txt
admindojo-0.1.28.dist-info/top_level.txt
admindojo-0.1.28.dist-info/RECORD
