Metadata-Version: 2.1
Name: admindojo
Version: 0.1.28
Summary: The admindojo client for VMs
Home-page: https://github.com/admindojo/admindojo-client
Author: Marvin Heimbrodt
Author-email: marvin@6uhrmittag.de
License: MIT license
Keywords: admindojo
Platform: UNKNOWN
Classifier: Development Status :: 4 - Beta
Classifier: Intended Audience :: Developers
Classifier: License :: OSI Approved :: MIT License
Classifier: Natural Language :: English
Classifier: Programming Language :: Python :: 3
Classifier: Programming Language :: Python :: 3.4
Classifier: Programming Language :: Python :: 3.5
Classifier: Programming Language :: Python :: 3.6
Classifier: Programming Language :: Python :: 3.7
Requires-Dist: Click (>=6.0)
Requires-Dist: termcolor
Requires-Dist: click-default-group
